ytrie/__init__.py
ytrie/api.py
ytrie-0.1.0.dist-info/top_level.txt
ytrie-0.1.0.dist-info/METADATA
ytrie-0.1.0.dist-info/DESCRIPTION.rst
ytrie-0.1.0.dist-info/metadata.json
ytrie-0.1.0.dist-info/WHEEL
ytrie-0.1.0.dist-info/RECORD
